ibm_wmla/__init__.py
ibm_wmla/common.py
ibm_wmla/edi_authentication.py
ibm_wmla/edi_token.py
ibm_wmla/version.py
ibm_wmla/wmla_api_edi_v2.py
ibm_wmla/wmla_api_v1.py
ibm_wmla-0.1.1.dist-info/LICENSE
ibm_wmla-0.1.1.dist-info/WHEEL
ibm_wmla-0.1.1.dist-info/METADATA
ibm_wmla-0.1.1.dist-info/RECORD
